Data_Structure_Hub/__init__.py
Data_Structure_Hub/queue.py
Data_Structure_Hub/stack.py
Data_Structure_Hub/graph/__init__.py
Data_Structure_Hub/graph/directed.py
Data_Structure_Hub/graph/graph.py
Data_Structure_Hub/graph/weighted.py
Data_Structure_Hub/linked_list/__init__.py
Data_Structure_Hub/linked_list/circular.py
Data_Structure_Hub/linked_list/doubly.py
Data_Structure_Hub/linked_list/singly.py
Data_Structure_Hub/tree/__init__.py
Data_Structure_Hub/tree/avl_tree.py
Data_Structure_Hub/tree/binary_search_tree.py
Data_Structure_Hub/tree/binary_tree.py
Data_Structure_Hub/tree/heap.py
data_structure_hub-0.2.2.dist-info/licenses/LICENSE
data_structure_hub-0.2.2.dist-info/METADATA
data_structure_hub-0.2.2.dist-info/WHEEL
data_structure_hub-0.2.2.dist-info/top_level.txt
data_structure_hub-0.2.2.dist-info/RECORD
