Metadata-Version: 2.4
Name: Data_Structure_Hub
Version: 0.2.2
Summary: A Python package with basic data structures
Author: Yashashvi bhardwaj
Author-email: yashashvibhardwaj@gmail.com
Classifier: Programming Language :: Python :: 3
Classifier: License :: OSI Approved :: MIT License
Classifier: Operating System :: OS Independent
Requires-Python: >=3.6
License-File: LICENSE
Dynamic: author
Dynamic: author-email
Dynamic: classifier
Dynamic: description
Dynamic: description-content-type
Dynamic: license-file
Dynamic: requires-python
Dynamic: summary
